damn/__init__.py
damn/processors.py
damn/settings.py
damn/templatetags/__init__.py
damn/templatetags/damn.py
django_damn-0.4.0.dist-info/LICENSE
django_damn-0.4.0.dist-info/METADATA
django_damn-0.4.0.dist-info/WHEEL
django_damn-0.4.0.dist-info/RECORD
