Metadata-Version: 2.1
Name: django-damn
Version: 0.4.0
Summary: Django asset dependency management.
Home-page: https://github.com/funkybob/django-amn
License: MIT
Keywords: django,assets
Author: Curtis Maloney
Author-email: curtis@tinbrain.net
Requires-Python: >=3.6,<4.0
Classifier: License :: OSI Approved :: MIT License
Classifier: Programming Language :: Python :: 3
Classifier: Programming Language :: Python :: 3.6
Classifier: Programming Language :: Python :: 3.7
Classifier: Programming Language :: Python :: 3.8
Classifier: Programming Language :: Python :: 3.9
Classifier: Programming Language :: Python :: 3.10
Classifier: Programming Language :: Python :: 3.11
Classifier: Programming Language :: Python :: 3.12
Requires-Dist: django (>3.0)
